Workbook

Sheet category_analysis
A3: Row Labels | B3: total Net Sales
A4: Beauty | B4: 682988.53
A5: Clothing | B5: 3335870.2
A6: Electronics | B6: 31956974
A7: Home & Kitchen | B7: 4773876.6
A8: Sports | B8: 1318368.7
A9: Grand Total | B9: 42068078

Sheet city sales analysis 
A3: Row Labels | B3: Sum of Net_Sales
A4: Mumbai | B4: 528706.57
A5: Gurugram | B5: 380414.41
A6: Noida | B6: 218201.65
A7: Lucknow | B7: 188859.43
A8: Bengaluru | B8: 182875.86
A9: Hyderabad | B9: 138920.13
A10: Chennai | B10: 116026.17
A11: Kolkata | B11: 110493.73
A12: Pune | B12: 94012.43
A13: Delhi | B13: 90962.88
A14: Jaipur | B14: 89602.65
A15: Ahmedabad | B15: 70919.86
A16: Grand Total | B16: 2209995.8

Sheet regional sales analysis
A3: Row Labels | B3: Sum of Net_Sales
A4: East | B4: 2759550.5
A5: North | B5: 13601758
A6: South | B6: 7120107.2
A7: West | B7: 8475558.4
A8: Grand Total | B8: 31956974

Sheet payment method analysis
A3: Row Labels | B3: Sum of Net_Sales | C3: Count of Order_ID
A4: UPI | B4: 14905206 | C4: 1775
A5: Credit Card | B5: 12537192 | C5: 1375
A6: Debit Card | B6: 6491415.6 | C6: 828
A7: Net Banking | B7: 5906439.8 | C7: 678
A8: Cash on Delivery | B8: 2227824.5 | C8: 344
A9: Grand Total | B9: 42068078 | C9: 5000

Sheet discount analysis
A3: Row Labels | B3: Sum of Net_Sales | C3: Sum of Profit
A4: 0.1 | B4: 8771686.2 | C4: 1405243.7
A5: 0.15 | B5: 7470059.3 | C5: 1061547.8
A6: 0.05 | B6: 6338501.6 | C6: 1119684.2
A7: 0 | B7: 5175320 | C7: 974182.16
A8: 0.2 | B8: 4216725.6 | C8: 536523.84
A9: 0.25 | B9: 2064183.8 | C9: 244522.4
A10: 0.13 | B10: 1495411.7 | C10: 231124.67
A11: 0.18 | B11: 1429044.3 | C11: 180921.72
A12: 0.08 | B12: 1415524 | C12: 232000.57
A13: 0.03 | B13: 1157524.3 | C13: 205521.82
A14: 0.23 | B14: 971211.78 | C14: 108118.46
A15: 0.3 | B15: 907895.1 | C15: 100952.39
... A17: 0.33 | B17: 235664.46 | C17: 20504.08
A18: Grand Total | B18: 42068078 | C18: 6465647.4

Sheet shipping mode analysis
A3: Row Labels | B3: Sum of Net_Sales | C3: Count of Order_ID
A4: Standard | B4: 25825249 | C4: 3101
A5: Express | B5: 12367288 | C5: 1391
A6: Same Day | B6: 3875541 | C6: 508
A7: Grand Total | B7: 42068078 | C7: 5000

Sheet top 10 CUSTOMERS by sales 
A3: Row Labels | B3: Sum of Net_Sales
A4: CUST1078 | B4: 369782.61
A5: CUST1702 | B5: 312673.68
A6: CUST1384 | B6: 306977.86
A7: CUST1339 | B7: 304624.03
A8: CUST1226 | B8: 302152.09
A9: CUST1413 | B9: 300362.28
A10: CUST1037 | B10: 292033.65
A11: CUST1476 | B11: 291820.4
A12: CUST1035 | B12: 291285.7
A13: CUST1653 | B13: 289915.13
A14: Grand Total | B14: 3061627.4

Sheet TOP 10 PRODUCT BY SALES
A1: Row Labels | B1: Sum of Net_Sales
A2: Laptop | B2: 21164647
A3: Smartphone | B3: 8330666.8
A4: Office Chair | B4: 2013864.3
A5: Wireless Earbuds | B5: 1162112.5
A6: Mixer Grinder | B6: 1080316.2
A7: Cookware Set | B7: 993898.59
A8: Sneakers | B8: 887494.86
A9: Dress | B9: 707166.24
A10: Jeans | B10: 613710.86
A11: Cricket Bat | B11: 535885.56
A12: Grand Total | B12: 37489763

Sheet subcategory analysis
A3: Row Labels | B3: Sum of Net_Sales | C3: Sum of Profit
A4: Beauty | B4: 682988.53 | C4: 235353.64
A5: Fragrance | B5: 308314.32 | C5: 105839.82
A6: Skincare | B6: 227380.11 | C6: 78215.6
A7: Haircare | B7: 147294.1 | C7: 51298.22
A8: Clothing | B8: 3335870.2 | C8: 948189.34
A9: Footwear | B9: 1340040.5 | C9: 380781.19
A10: Women | B10: 1141587.9 | C10: 325472.78
A11: Men | B11: 854241.82 | C11: 241935.37
A12: Electronics | B12: 31956974 | C12: 3980484.1
A13: Computers | B13: 21164647 | C13: 2641632.8
A14: Mobiles | B14: 9492779.3 | C14: 1177143.8
A15: Accessories | B15: 1299547.4 | C15: 161707.49
... A23: Grand Total | B23: 42068078 | C23: 6465647.4

Sheet dashboard
A1: E-COMMERCE SALES ANALYSIS DASHBOARD
A3: TOTAL SALES | B3: =SUM(Sales_Data!N2:N5001) -> 42068078
A4: TOTAL PROFIT | B4: =SUM(Sales_Data!O2:O5001) -> 6465647.4
A5: TOTAL ORDERS | B5: =COUNTA(Sales_Data!A2:A5001) -> 5000
A6: TOTAL CUSTOMERS | B6: =COUNTA((_xlfn.UNIQUE(Sales_Data!C2:C5001))) -> 796
A7: TOTAL QUANTITY | B7: =SUM(Sales_Data!I2:I5001) -> 8618
A8: AVERAGE ORDER VALUE | B8: =B3/B5 -> 8413.6156

Sheet monthly sale analysisss
A3: Row Labels | B3: Sum of Net_Sales
A4: 2024 | B4: 22647274
A5: Jan | B5: 1684821.2
A6: Feb | B6: 2705015
A7: Mar | B7: 1980293.9
A8: Apr | B8: 2009764.4
A9: May | B9: 1739737.3
A10: Jun | B10: 1687865.5
A11: Jul | B11: 1225524.8
A12: Aug | B12: 1621665
A13: Sep | B13: 1574973.1
A14: Oct | B14: 2333193.5
A15: Nov | B15: 1891154.6
A16: Dec | B16: 2193265.5
A17: 2025 | B17: 19420804
A18: Jan | B18: 1183737
A19: Feb | B19: 1765095.3
A20: Mar | B20: 1712258.3
A21: Apr | B21: 1716785.1
A22: May | B22: 1956974.6
A23: Jun | B23: 1652862.2
A24: Jul | B24: 1650235
A25: Aug | B25: 1720086.4
A26: Sep | B26: 1613629.7
A27: Oct | B27: 1409854.5
A28: Nov | B28: 1209657.6
A29: Dec | B29: 1829628.6
A30: Grand Total | B30: 42068078

Sheet PROFIT BY CATEGORY
A3: Row Labels | B3: Sum of Profit
A4: Beauty | B4: 235353.64
A5: Clothing | B5: 948189.34
A6: Electronics | B6: 3980484.1
A7: Home & Kitchen | B7: 979112.35
A8: Sports | B8: 322507.95
A9: Grand Total | B9: 6465647.4

Sheet Sales_Data
A1: Order_ID | B1: Order_date | C1: Customer_ID | D1: Customer_Name | E1: Product_ID | F1: Product_Name | G1: Category | H1: Sub_Category | I1: Quantity | J1: Unit_Price | K1: Sales | L1: Discount | M1: Discount_Amount | N1: Net_Sales | O1: Profit | P1: City | Q1: State | R1: Region | S1: Payment_Method | T1: Shipping_Mode | U1: Year | V1: Month_Number | W1: Month | X1: Profit_Margin | Y1: Check_Net_Margin | Z1: Net_Sales_Check
A2: ORD100909 | B2: 45406 | C2: CUST1658 | D2: Customer_0658 | E2: P2010 | F2: Dress | G2: Clothing | H2: Women | I2: 1 | J2: 1999 | K2: 1999 | L2: 0.1 | M2: 199.9 | N2: 1799.1 | O2: 521.74 | P2: Kolkata | Q2: West Bengal | R2: East | S2: Cash on Delivery | T2: Standard | U2: =YEAR(B2) -> 2024 | V2: =MONTH(B2) -> 4 | W2: =TEXT(B2,"mmmm") -> April | X2: 0.29 | Y2: =ROUND(N2-(M2),2) -> 1599.2 | Z2: {=IF(roud(N2,2)=ROUND(Z2,2),"ok","error")} -> 0
A3: ORD101378 | B3: 45317 | C3: CUST1659 | D3: Customer_0555 | E3: P2009 | F3: Kurti | G3: Clothing | H3: Women | I3: 1 | J3: 1199 | K3: 1199 | L3: 0.05 | M3: 59.95 | N3: 1139.05 | O3: 347.41 | P3: Chennai | Q3: Tamil Nadu | R3: South | S3: UPI | T3: Same Day | U3: =YEAR(B3) -> 2024 | V3: =MONTH(B3) -> 1 | W3: =TEXT(B3,"mmmm") -> January | X3: 0.305 | Y3: =ROUND(N3-(M3),2) -> 1079.1 | Z3: {=IF(roud(N3,2)=ROUND(Z3,2),"ok","error")} -> 0
A4: ORD101940 | B4: 45573 | C4: CUST1660 | D4: Customer_0799 | E4: P2014 | F4: Cookware Set | G4: Home & Kitchen | H4: Kitchen | I4: 1 | J4: 2999 | K4: 2999 | L4: 0.1 | M4: 299.9 | N4: 2699.1 | O4: 566.81 | P4: Kolkata | Q4: West Bengal | R4: East | S4: Debit Card | T4: Express | U4: =YEAR(B4) -> 2024 | V4: =MONTH(B4) -> 10 | W4: =TEXT(B4,"mmmm") -> October | X4: 0.21 | Y4: =ROUND(N4-(M4),2) -> 2399.2 | Z4: {=IF(roud(N4,2)=ROUND(Z4,2),"ok","error")} -> 0
A5: ORD101977 | B5: 45542 | C5: CUST1661 | D5: Customer_0787 | E5: P2003 | F5: Laptop | G5: Electronics | H5: Computers | I5: 1 | J5: 59999 | K5: 59999 | L5: 0.15 | M5: 8999.85 | N5: 50999.15 | O5: 5864.9 | P5: Noida | Q5: Uttar Pradesh | R5: North | S5: Debit Card | T5: Same Day | U5: =YEAR(B5) -> 2024 | V5: =MONTH(B5) -> 9 | W5: =TEXT(B5,"mmmm") -> September | X5: 0.115 | Y5: =ROUND(N5-(M5),2) -> 41999.3 | Z5: {=IF(roud(N5,2)=ROUND(Z5,2),"ok","error")} -> 0
A6: ORD102078 | B6: 45520 | C6: CUST1228 | D6: Customer_0228 | E6: P2005 | F6: Keyboard | G6: Electronics | H6: Accessories | I6: 2 | J6: 1299 | K6: 2598 | L6: 0.3 | M6: 779.4 | N6: 1818.6 | O6: 127.3 | P6: Chennai | Q6: Tamil Nadu | R6: South | S6: UPI | T6: Standard | U6: =YEAR(B6) -> 2024 | V6: =MONTH(B6) -> 8 | W6: =TEXT(B6,"mmmm") -> August | X6: 0.07 | Y6: =ROUND(N6-(M6),2) -> 1039.2 | Z6: {=IF(roud(N6,2)=ROUND(Z6,2),"ok","error")} -> 0
A7: ORD102301 | B7: 45434 | C7: CUST1286 | D7: Customer_0286 | E7: P2006 | F7: Power Bank | G7: Electronics | H7: Accessories | I7: 1 | J7: 1499 | K7: 1499 | L7: 0.2 | M7: 299.8 | N7: 1199.2 | O7: 119.92 | P7: Kolkata | Q7: West Bengal | R7: East | S7: Debit Card | T7: Standard | U7: =YEAR(B7) -> 2024 | V7: =MONTH(B7) -> 5 | W7: =TEXT(B7,"mmmm") -> May | X7: 0.1 | Y7: =ROUND(N7-(M7),2) -> 899.4 | Z7: {=IF(roud(N7,2)=ROUND(Z7,2),"ok","error")} -> 0
A8: ORD103524 | B8: 45396 | C8: CUST1175 | D8: Customer_0175 | E8: P2013 | F8: Mixer Grinder | G8: Home & Kitchen | H8: Kitchen | I8: 1 | J8: 3499 | K8: 3499 | L8: 0.2 | M8: 699.8 | N8: 2799.2 | O8: 503.86 | P8: Delhi | Q8: Delhi | R8: North | S8: Cash on Delivery | T8: Same Day | U8: =YEAR(B8) -> 2024 | V8: =MONTH(B8) -> 4 | W8: =TEXT(B8,"mmmm") -> April | X8: 0.18 | Y8: =ROUND(N8-(M8),2) -> 2099.4 | Z8: {=IF(roud(N8,2)=ROUND(Z8,2),"ok","error")} -> 0
A9: ORD103532 | B9: 45984 | C9: CUST1311 | D9: Customer_0311 | E9: P2012 | F9: Sandals | G9: Clothing | H9: Footwear | I9: 4 | J9: 1299 | K9: 5196 | L9: 0.15 | M9: 779.4 | N9: 4416.6 | O9: 1214.57 | P9: Gurugram | Q9: Haryana | R9: North | S9: UPI | T9: Standard | U9: =YEAR(B9) -> 2025 | V9: =MONTH(B9) -> 11 | W9: =TEXT(B9,"mmmm") -> November | X9: 0.275 | Y9: =ROUND(N9-(M9),2) -> 3637.2 | Z9: {=IF(roud(N9,2)=ROUND(Z9,2),"ok","error")} -> 0
A10: ORD101696 | B10: 45850 | C10: CUST1071 | D10: Customer_0071 | E10: P2014 | F10: Cookware Set | G10: Home & Kitchen | H10: Kitchen | I10: 2 | J10: 2999 | K10: 5998 | L10: 0.15 | M10: 899.7 | N10: 5098.3 | O10: 994.17 | P10: Lucknow | Q10: Uttar Pradesh | R10: North | S10: UPI | T10: Standard | U10: =YEAR(B10) -> 2025 | V10: =MONTH(B10) -> 7 | W10: =TEXT(B10,"mmmm") -> July | X10: 0.195 | Y10: =ROUND(N10-(M10),2) -> 4198.6 | Z10: {=IF(roud(N10,2)=ROUND(Z10,2),"ok","error")} -> 0
A11: ORD101709 | B11: 45381 | C11: CUST1085 | D11: Customer_0085 | E11: P2013 | F11: Mixer Grinder | G11: Home & Kitchen | H11: Kitchen | I11: 1 | J11: 3499 | K11: 3499 | L11: 0.05 | M11: 174.95 | N11: 3324.05 | O11: 747.91 | P11: Gurugram | Q11: Haryana | R11: North | S11: Net Banking | T11: Express | U11: =YEAR(B11) -> 2024 | V11: =MONTH(B11) -> 3 | W11: =TEXT(B11,"mmmm") -> March | X11: 0.225 | Y11: =ROUND(N11-(M11),2) -> 3149.1 | Z11: {=IF(roud(N11,2)=ROUND(Z11,2),"ok","error")} -> 0
A12: ORD103040 | B12: 45896 | C12: CUST1055 | D12: Customer_0055 | E12: P2017 | F12: Office Chair | G12: Home & Kitchen | H12: Furniture | I12: 5 | J12: 5999 | K12: 29995 | L12: 0.15 | M12: 4499.25 | N12: 25495.75 | O12: 4971.67 | P12: Hyderabad | Q12: Telangana | R12: South | S12: Credit Card | T12: Standard | U12: =YEAR(B12) -> 2025 | V12: =MONTH(B12) -> 8 | W12: =TEXT(B12,"mmmm") -> August | X12: 0.195 | Y12: =ROUND(N12-(M12),2) -> 20996.5 | Z12: {=IF(roud(N12,2)=ROUND(Z12,2),"ok","error")} -> 0
A13: ORD101017 | B13: 45724 | C13: CUST1241 | D13: Customer_0241 | E13: P2025 | F13: Football | G13: Sports | H13: Outdoor | I13: 1 | J13: 999 | K13: 999 | L13: 0.25 | M13: 249.75 | N13: 749.25 | O13: 153.6 | P13: Gurugram | Q13: Haryana | R13: North | S13: UPI | T13: Same Day | U13: =YEAR(B13) -> 2025 | V13: =MONTH(B13) -> 3 | W13: =TEXT(B13,"mmmm") -> March | X13: 0.205 | Y13: =ROUND(N13-(M13),2) -> 499.5 | Z13: {=IF(roud(N13,2)=ROUND(Z13,2),"ok","error")} -> 0
... A5001: ORD104560 | B5001: 45543 | C5001: CUST1112 | D5001: Customer_0112 | E5001: P2008 | F5001: Jeans | G5001: clothing | H5001: Men | I5001: 2 | J5001: 1799 | K5001: 3598 | L5001: 0.33 | M5001: 1187.34 | N5001: 2410.66 | O5001: 532.76 | P5001: Ahmedabad | Q5001: Gujarat | R5001: West | S5001: Credit Card | T5001: Same Day | U5001: =YEAR(B5001) -> 2024 | V5001: =MONTH(B5001) -> 9 | W5001: =TEXT(B5001,"mmmm") -> September | X5001: 0.221 | Y5001: =ROUND(N5001-(M5001),2) -> 1223.32 | Z5001: {=IF(roud(N5001,2)=ROUND(Z5001,2),"ok","error")} -> 0

Sheet data quality 
A1: DATA QUALITY CHECK
A3: COLUMN | B3: RESULT | C3: STATUS
A4: ORDER_ID | B4: =COUNTBLANK(Sales_Data!A2:A5001) -> 0
A5: ORDER_DATE | B5: =COUNTBLANK(Sales_Data!B2:B5001) -> 0
A6: CUSTOMER_ID | B6: =COUNTBLANK(Sales_Data!C2:C5001) -> 0
A7: CUSTOMER_NAME | B7: =COUNTBLANK(Sales_Data!D2:D5001) -> 0
A8: PRODUCT_ID | B8: =COUNTBLANK(Sales_Data!E2:E5001) -> 0
A9: PRODUCT-name | B9: =COUNTBLANK(Sales_Data!F2:F5001) -> 0
A10: CATEGORY | B10: =COUNTBLANK(Sales_Data!G2:G5001) -> 0
A11: SUB_CATEGORY | B11: =COUNTBLANK(Sales_Data!H2:H5001) -> 0
A12: QUANTITY | B12: =COUNTBLANK(Sales_Data!I2:I5001) -> 0
A13: UNIT_PRICE | B13: =COUNTBLANK(Sales_Data!J2:J5001) -> 0
A14: SALES | B14: =COUNTBLANK(Sales_Data!K2:K5001) -> 0
A15: DISCOUNT | B15: =COUNTBLANK(Sales_Data!L2:L5001) -> 0
A16: DISOUNT_AMOUT | B16: =COUNTBLANK(Sales_Data!M2:M5001) -> 0
A17: NET_SALES | B17: =COUNTBLANK(Sales_Data!O2:O5001) -> 0
A18: PROFIT | B18: =COUNTBLANK(Sales_Data!O2:O5001) -> 0
A19: CITY | B19: =COUNTBLANK(Sales_Data!P2:P5001) -> 0
A20: STATE | B20: =COUNTBLANK(Sales_Data!Q2:Q5001) -> 0
A21: REGION | B21: =COUNTBLANK(Sales_Data!R2:R5001) -> 0
A22: PAYMENT_METHOD | B22: =COUNTBLANK(Sales_Data!S2:S5001) -> 0
A23: SHIPPING_MODE | B23: =COUNTBLANK(Sales_Data!T2:T5001) -> 0
A24: YEAR | B24: =COUNTBLANK(Sales_Data!V2:V5001) -> 0
A25: MONTH_NUMBER | B25: =COUNTBLANK(Sales_Data!W2:W5001) -> 0
A26: MONTH | B26: =COUNTBLANK(Sales_Data!W2:W5001) -> 0
A27: PROFIT_MARGIN | B27: =COUNTBLANK(Sales_Data!X2:X5001) -> 0

Sheet Data_Dictionary
A1: Column | B1: Description | C1: Data_Type
A2: Order_ID | B2: Unique order identifier | C2: Text
A3: Order_Date | B3: Date of purchase | C3: Date
A4: Customer_ID | B4: Unique customer identifier | C4: Text
A5: Customer_Name | B5: Customer display name | C5: Text
A6: Product_ID | B6: Unique product identifier | C6: Text
A7: Product_Name | B7: Product purchased | C7: Text
A8: Category | B8: Main product category | C8: Text
A9: Sub_Category | B9: Product sub-category | C9: Text
A10: Quantity | B10: Units purchased | C10: Integer
A11: Unit_Price | B11: Price per unit before discount | C11: Currency
A12: Sales | B12: Gross sales before discount | C12: Currency
... A25: Profit_Margin | B25: Profit divided by Net Sales | C25: Percentage
